canatax/__init__.py
canatax/enums.py
canatax/exc.py
canatax/tax_estimate.py
canatax/utils.py
canatax/calculators/__init__.py
canatax/calculators/base_calculator.py
canatax/calculators/income_calculator.py
canatax/calculators/sales_calculator.py
canatax/rates/__init__.py
canatax/rates/income/__init__.py
canatax/rates/income/base.py
canatax/rates/income/current_contributions.py
canatax/rates/income/current_tax.py
canatax/rates/income/contribution_rates/__init__.py
canatax/rates/income/contribution_rates/rates_2025.py
canatax/rates/income/tax_rates/__init__.py
canatax/rates/income/tax_rates/rates_2024.py
canatax/rates/income/tax_rates/rates_2025.py
canatax/rates/sales/__init__.py
canatax/rates/sales/base.py
canatax/rates/sales/current_sales_tax.py
canatax/rates/sales/sales_tax_rates/__init__.py
canatax/rates/sales/sales_tax_rates/rates_2024.py
canatax/rates/sales/sales_tax_rates/rates_2025.py
canatax-2.0.1.dist-info/licenses/LICENSE
canatax-2.0.1.dist-info/METADATA
canatax-2.0.1.dist-info/WHEEL
canatax-2.0.1.dist-info/top_level.txt
canatax-2.0.1.dist-info/RECORD
