Metadata-Version: 2.4
Name: canatax
Version: 2.0.1
Summary: An easy-to-use, dependency-free Canadian sales and income tax calculator.
Home-page: https://github.com/firstflush/canatax
Author: Michael Pearce
Author-email: firstflush@protonmail.com
License: MIT
Project-URL: Homepage, https://github.com/firstflush/canatax
Project-URL: Bug Tracker, https://github.com/firstflush/canatax/issues
Project-URL: Buy Me a Coffee, https://www.buymeacoffee.com/FirstFlush
Keywords: canada tax cpp ei qpp gst hst pst qst income sales payroll
Classifier: Development Status :: 5 - Production/Stable
Classifier: Intended Audience :: Developers
Classifier: Intended Audience :: Financial and Insurance Industry
Classifier: Topic :: Office/Business :: Financial :: Accounting
Classifier: Topic :: Software Development :: Libraries :: Python Modules
Classifier: Programming Language :: Python :: 3
Classifier: Programming Language :: Python :: 3.10
Classifier: License :: OSI Approved :: MIT License
Classifier: Operating System :: OS Independent
Requires-Python: >=3.10
License-File: LICENSE
Dynamic: author
Dynamic: author-email
Dynamic: classifier
Dynamic: description
Dynamic: description-content-type
Dynamic: home-page
Dynamic: keywords
Dynamic: license
Dynamic: license-file
Dynamic: project-url
Dynamic: requires-python
Dynamic: summary
